interval_sdk/__init__.py
interval_sdk/classes/__init__.py
interval_sdk/classes/action.py
interval_sdk/classes/component.py
interval_sdk/classes/interval_file.py
interval_sdk/classes/io.py
interval_sdk/classes/io_client.py
interval_sdk/classes/io_error.py
interval_sdk/classes/io_promise.py
interval_sdk/classes/isocket.py
interval_sdk/classes/layout.py
interval_sdk/classes/logger.py
interval_sdk/classes/page.py
interval_sdk/classes/rpc.py
interval_sdk/classes/transaction_loading_state.py
interval_sdk/components/__init__.py
interval_sdk/components/grid.py
interval_sdk/components/table.py
interval_sdk/handlers.py
interval_sdk/internal_rpc_schema.py
interval_sdk/io_schema.py
interval_sdk/main.py
interval_sdk/superjson/__init__.py
interval_sdk/superjson/main.py
interval_sdk/superjson/plainer.py
interval_sdk/superjson/tests/__init__.py
interval_sdk/superjson/tests/node-only-types.js
interval_sdk/superjson/tests/round-trip-superjson.js
interval_sdk/superjson/tests/test_superjson.py
interval_sdk/superjson/transformer.py
interval_sdk/types.py
interval_sdk/util.py
interval_sdk-1.5.1.dist-info/METADATA
interval_sdk-1.5.1.dist-info/WHEEL
interval_sdk-1.5.1.dist-info/RECORD
