Metadata-Version: 2.1
Name: interval-sdk
Version: 1.5.1
Summary: The frontendless framework for high growth companies. Interval automatically generates apps by inlining the UI in your backend code. It's a faster and more maintainable way to build internal tools, rapid prototypes, and more.
Home-page: https://interval.com
Keywords: internal tool,app,ui,ui builder
Author: Jacob Mischka
Author-email: jacob@interval.com
Maintainer: Jacob Mischka
Maintainer-email: jacob@interval.com
Requires-Python: >=3.9,<4.0
Classifier: Programming Language :: Python :: 3
Classifier: Programming Language :: Python :: 3.9
Classifier: Programming Language :: Python :: 3.10
Classifier: Programming Language :: Python :: 3.11
Requires-Dist: aiodns (>=3.0.0,<4.0.0)
Requires-Dist: aiohttp (>=3.8.1,<4.0.0)
Requires-Dist: pydantic (>=1.9.0,<2.0.0)
Requires-Dist: typing-extensions (>=4.4.0,<5.0.0)
Requires-Dist: websockets (>=10.1,<11.0)
Project-URL: Documentation, https://interval.com/docs
Project-URL: Repository, https://github.com/interval/interval-py
